sphinx_paramlinks/__init__.py
sphinx_paramlinks/sphinx_paramlinks.css
sphinx_paramlinks/sphinx_paramlinks.py
sphinx_paramlinks-0.5.1.dist-info/LICENSE
sphinx_paramlinks-0.5.1.dist-info/METADATA
sphinx_paramlinks-0.5.1.dist-info/WHEEL
sphinx_paramlinks-0.5.1.dist-info/top_level.txt
sphinx_paramlinks-0.5.1.dist-info/RECORD
