Metadata-Version: 2.1
Name: sphinx-paramlinks
Version: 0.5.1
Summary: Allows param links in Sphinx function/method descriptions to be linkable
Home-page: http://github.com/sqlalchemyorg/sphinx-paramlinks
Author: Mike Bayer
Author-email: mike@zzzcomputing.com
License: MIT
Keywords: sphinx
Platform: UNKNOWN
Classifier: Development Status :: 3 - Alpha
Classifier: Environment :: Console
Classifier: Intended Audience :: Developers
Classifier: Programming Language :: Python
Classifier: Programming Language :: Python :: 3
Classifier: Programming Language :: Python :: Implementation :: CPython
Classifier: Programming Language :: Python :: Implementation :: PyPy
Classifier: Topic :: Documentation
